spacemakerlog3/__init__.py
spacemakerlog3/__version__.py
spacemakerlog3/log.py
spacemakerlog3/utils.py
spacemakerlog3-0.3.1.dist-info/LICENSE
spacemakerlog3-0.3.1.dist-info/METADATA
spacemakerlog3-0.3.1.dist-info/WHEEL
spacemakerlog3-0.3.1.dist-info/top_level.txt
spacemakerlog3-0.3.1.dist-info/RECORD
