Metadata-Version: 2.1
Name: spacemakerlog3
Version: 0.3.1
Summary: For structured logging.
Home-page: https://github.com/spacemakerai/spacemaker-logging/tree/master/python3
Author: Spacemaker
Author-email: hello@spacemaker.ai
License: MIT
Platform: UNKNOWN
Classifier: License :: OSI Approved :: MIT License
Classifier: Programming Language :: Python
Classifier: Programming Language :: Python :: 3
Classifier: Programming Language :: Python :: 3.6
Classifier: Programming Language :: Python :: Implementation :: CPython
Classifier: Programming Language :: Python :: Implementation :: PyPy
Requires-Python: >=3.6.0
Requires-Dist: structlog
Requires-Dist: python-json-logger
